modflow_devtools/__init__.py
modflow_devtools/build.py
modflow_devtools/dfn.py
modflow_devtools/dfn2toml.py
modflow_devtools/download.py
modflow_devtools/fixtures.py
modflow_devtools/imports.py
modflow_devtools/latex.py
modflow_devtools/make_registry.py
modflow_devtools/markers.py
modflow_devtools/misc.py
modflow_devtools/models.py
modflow_devtools/ostags.py
modflow_devtools/snapshots.py
modflow_devtools/zip.py
modflow_devtools/registry/examples.toml
modflow_devtools/registry/models.toml
modflow_devtools/registry/registry.toml
modflow_devtools-1.7.0.dist-info/METADATA
modflow_devtools-1.7.0.dist-info/WHEEL
modflow_devtools-1.7.0.dist-info/licenses/LICENSE.md
modflow_devtools-1.7.0.dist-info/RECORD
