Metadata-Version: 2.4
Name: modflow-devtools
Version: 1.7.0
Summary: Python tools for MODFLOW development
Project-URL: Documentation, https://modflow-devtools.readthedocs.io/en/latest/
Project-URL: Bug Tracker, https://github.com/MODFLOW-ORG/modflow-devtools/issues
Project-URL: Source Code, https://github.com/MODFLOW-ORG/modflow-devtools
Author-email: "Joseph D. Hughes" <modflow@usgs.gov>, Michael Reno <mreno@ucar.edu>, Mike Taves <mwtoews@gmail.com>, Wes Bonelli <wbonelli@ucar.edu>
Maintainer-email: "Joseph D. Hughes" <modflow@usgs.gov>
License: CC0
License-File: LICENSE.md
Keywords: MODFLOW,development,groundwater,hydrogeology,utilities
Classifier: Development Status :: 5 - Production/Stable
Classifier: Intended Audience :: Science/Research
Classifier: License :: CC0 1.0 Universal (CC0 1.0) Public Domain Dedication
Classifier: Programming Language :: Python :: 3
Classifier: Programming Language :: Python :: 3 :: Only
Classifier: Programming Language :: Python :: 3.10
Classifier: Programming Language :: Python :: 3.11
Classifier: Programming Language :: Python :: 3.12
Classifier: Programming Language :: Python :: 3.13
Classifier: Topic :: Scientific/Engineering :: Hydrology
Requires-Python: >=3.10
Provides-Extra: build
Requires-Dist: build; extra == 'build'
Requires-Dist: twine; extra == 'build'
Provides-Extra: dev
Requires-Dist: boltons; extra == 'dev'
Requires-Dist: codespell[toml]; extra == 'dev'
Requires-Dist: coverage; extra == 'dev'
Requires-Dist: filelock; extra == 'dev'
Requires-Dist: flaky; extra == 'dev'
Requires-Dist: meson!=0.63.0; extra == 'dev'
Requires-Dist: mypy; extra == 'dev'
Requires-Dist: myst-parser; extra == 'dev'
Requires-Dist: ninja; extra == 'dev'
Requires-Dist: numpy; extra == 'dev'
Requires-Dist: pandas; extra == 'dev'
Requires-Dist: pooch; extra == 'dev'
Requires-Dist: pytest!=8.1.0; extra == 'dev'
Requires-Dist: pytest-cov; extra == 'dev'
Requires-Dist: pytest-dotenv; extra == 'dev'
Requires-Dist: pytest-xdist; extra == 'dev'
Requires-Dist: pyyaml; extra == 'dev'
Requires-Dist: ruff; extra == 'dev'
Requires-Dist: sphinx; extra == 'dev'
Requires-Dist: sphinx-rtd-theme; extra == 'dev'
Requires-Dist: syrupy; extra == 'dev'
Requires-Dist: tomli; extra == 'dev'
Requires-Dist: tomli-w; extra == 'dev'
Provides-Extra: dfn
Requires-Dist: boltons; extra == 'dfn'
Requires-Dist: tomli; extra == 'dfn'
Requires-Dist: tomli-w; extra == 'dfn'
Provides-Extra: docs
Requires-Dist: myst-parser; extra == 'docs'
Requires-Dist: sphinx; extra == 'docs'
Requires-Dist: sphinx-rtd-theme; extra == 'docs'
Provides-Extra: lint
Requires-Dist: codespell[toml]; extra == 'lint'
Requires-Dist: mypy; extra == 'lint'
Requires-Dist: ruff; extra == 'lint'
Provides-Extra: models
Requires-Dist: boltons; extra == 'models'
Requires-Dist: filelock; extra == 'models'
Requires-Dist: pooch; extra == 'models'
Requires-Dist: tomli; extra == 'models'
Requires-Dist: tomli-w; extra == 'models'
Provides-Extra: test
Requires-Dist: codespell[toml]; extra == 'test'
Requires-Dist: coverage; extra == 'test'
Requires-Dist: filelock; extra == 'test'
Requires-Dist: flaky; extra == 'test'
Requires-Dist: meson!=0.63.0; extra == 'test'
Requires-Dist: mypy; extra == 'test'
Requires-Dist: ninja; extra == 'test'
Requires-Dist: numpy; extra == 'test'
Requires-Dist: pandas; extra == 'test'
Requires-Dist: pytest!=8.1.0; extra == 'test'
Requires-Dist: pytest-cov; extra == 'test'
Requires-Dist: pytest-dotenv; extra == 'test'
Requires-Dist: pytest-xdist; extra == 'test'
Requires-Dist: pyyaml; extra == 'test'
Requires-Dist: ruff; extra == 'test'
Requires-Dist: syrupy; extra == 'test'
